calculator_pkg_abhinav/__init__.py
calculator_pkg_abhinav/__main__.py
calculator_pkg_abhinav/calculator.py
calculator_pkg_abhinav/py.typed
calculator_pkg_abhinav/file_calculator/__init__.py
calculator_pkg_abhinav/file_calculator/file_calculator.py
calculator_pkg_abhinav/file_calculator/nums.csv
calculator_pkg_abhinav/tests/__init__.py
calculator_pkg_abhinav/tests/test_file_calculator.py
calculator_pkg_abhinav-0.6.0.dist-info/licenses/LICENSE.txt
calculator_pkg_abhinav-0.6.0.dist-info/METADATA
calculator_pkg_abhinav-0.6.0.dist-info/WHEEL
calculator_pkg_abhinav-0.6.0.dist-info/entry_points.txt
calculator_pkg_abhinav-0.6.0.dist-info/top_level.txt
calculator_pkg_abhinav-0.6.0.dist-info/RECORD
