Metadata-Version: 2.4
Name: calculator_pkg_abhinav
Version: 0.6.0
License-File: LICENSE.txt
Requires-Dist: tqdm~=4.0
Provides-Extra: test
Requires-Dist: pytest; extra == "test"
Requires-Dist: mypy; extra == "test"
Requires-Dist: ruff; extra == "test"
Requires-Dist: pre-commit; extra == "test"
Requires-Dist: tox; extra == "test"
Dynamic: license-file
